fft_calculations/__init__.py
fft_calculations/fft_calculations.py
fft_calculations-0.2.3.dist-info/METADATA
fft_calculations-0.2.3.dist-info/WHEEL
fft_calculations-0.2.3.dist-info/licenses/LICENSE
fft_calculations-0.2.3.dist-info/RECORD
