Metadata-Version: 2.4
Name: fft_calculations
Version: 0.2.3
Summary: A package with some fft utility functions
Project-URL: Homepage, https://github.com/kvdijken/fft_calculations
Author-email: kvdijken <sla_nippers_0x@icloud.com>
License-File: LICENSE
Classifier: License :: OSI Approved :: MIT License
Classifier: Operating System :: OS Independent
Classifier: Programming Language :: Python :: 3
Requires-Python: >=3.11
Requires-Dist: numpy
Requires-Dist: scipy
